seriallink/__init__.py
seriallink-1.1.0.dist-info/licenses/LICENSE
seriallink-1.1.0.dist-info/METADATA
seriallink-1.1.0.dist-info/WHEEL
seriallink-1.1.0.dist-info/top_level.txt
seriallink-1.1.0.dist-info/RECORD
