Metadata-Version: 2.4
Name: SerialLink
Version: 1.1.0
Summary: SerialLink is a Python library designed to simplify serial communication with microcontrollers
Home-page: https://github.com/Michael-Jalloh/SerialLink
Author: Michael Jalloh
Author-email: michaeljalloh19@gmail.com
License: MIT
Project-URL: issues, https://github.com/Michael-Jalloh/SerialLink/issues
Project-URL: source, https://github.com/Michael-Jalloh/SerialLink
Keywords: seriallink,serial,link,communication,microcontroller
Platform: any
Classifier: Development Status :: 4 - Beta
Classifier: Intended Audience :: Developers
Classifier: Topic :: Software Development :: Build Tools
Classifier: License :: OSI Approved :: MIT License
Classifier: Programming Language :: Python :: 3.7
Classifier: Programming Language :: Python :: 3.8
Classifier: Programming Language :: Python :: 3.9
Classifier: Programming Language :: Python :: 3.10
Classifier: Programming Language :: Python :: 3.11
Classifier: Programming Language :: Python :: 3.12
Classifier: Programming Language :: Python :: 3.13
License-File: LICENSE
Requires-Dist: pyserial
Dynamic: author
Dynamic: author-email
Dynamic: classifier
Dynamic: description
Dynamic: description-content-type
Dynamic: home-page
Dynamic: keywords
Dynamic: license
Dynamic: license-file
Dynamic: platform
Dynamic: project-url
Dynamic: requires-dist
Dynamic: summary
